circuit.v
`timescale 1ns / 1ps
`include "iob_lib.vh"

`define W = 32
module circuit
  #(
    parameter W = 32
    )
  (
   `INPUT(rst,1),
   `INPUT(clk,1),
   `INPUT(en,1),
   `INPUT(x,W),
   `OUTPUT(y,W)
   );
   `SIGNAL(cnt, 7)
   `SIGNAL(y_final, W)
   `SIGNAL(y_final_1, W)
   `SIGNAL2OUT(y, y_final)


   `SIGNAL(acc, W)
   `ACC_ARE(clk, rst, 1'b0, en, acc, x)

   `REG_RE(clk, rst, 1'b0, en & (cnt!=99), y_final_1, y_final)
   `COUNTER_RE(clk, rst, en & (cnt!=99), cnt)
   `COMB y_final = y_final_1 + y_final_1 + acc + (cnt == 1'b1);
endmodule

circuit_tb.v
`timescale 1ns / 1ps
`include "iob_lib.vh"

`define W 32

module circuit_tb;

   `CLOCK(clk, 10)
   `RESET(rst, 1, 10)
   `SIGNAL(en, 1)
   `SIGNAL(x, `W)
   `SIGNAL_OUT(y, `W)

   integer i;

   initial begin
      $dumpfile("circuit.vcd");
      $dumpvars();
      en=0;
      for (i=0; i<100; i=i+1) begin
         @(posedge clk) #1 x=$random%10; en=1;
         $display("%d: %d",i+1, y);
      end

      @(posedge clk) #100 $finish;

   end

   circuit
     #(
       .W(`W)
       )
   c0
     (
      .rst(rst),
      .clk(clk),
      .en(en),
      .x(x),
      .y(y)
      );


endmodule

circuit.vcd
$date
	Tue Nov 17 21:13:59 2020
$end
$version
	Icarus Verilog
$end
$timescale
	1ps
$end
$scope module circuit_tb $end
$var wire 32 ! y [31:0] $end
$var reg 1 " clk $end
$var reg 1 # en $end
$var reg 1 $ rst $end
$var reg 32 % x [31:0] $end
$var integer 32 & i [31:0] $end
$scope module c0 $end
$var wire 1 " clk $end
$var wire 1 # en $end
$var wire 1 $ rst $end
$var wire 32 ' x [31:0] $end
$var wire 32 ( y [31:0] $end
$var reg 32 ) acc [31:0] $end
$var reg 7 * cnt [6:0] $end
$var reg 32 + y_final [31:0] $end
$var reg 32 , y_final_1 [31:0] $end
$upscope $end
$upscope $end
$enddefinitions $end
#0
$dumpvars
bx ,
bx +
bx *
bx )
bx (
bx '
b0 &
bx %
0$
0#
1"
bx !
$end
#1000
b0 )
1$
#5000
0"
#10000
b0 !
b0 (
b0 +
b0 *
b0 ,
1"
#11000
b1 &
1#
b1000 %
b1000 '
0$
#15000
0"
#20000
b1001 !
b1001 (
b1001 +
b1 *
b1000 )
1"
#21000
b10 &
b11111111111111111111111111110111 %
b11111111111111111111111111110111 '
#25000
0"
#30000
b10001 !
b10001 (
b10001 +
b10 *
b1001 ,
b11111111111111111111111111111111 )
1"
#31000
b11 &
#35000
0"
#40000
b11000 !
b11000 (
b11000 +
b10001 ,
b11 *
b11111111111111111111111111110110 )
1"
#41000
b100 &
#45000
0"
#50000
b11101 !
b11101 (
b11101 +
b100 *
b11000 ,
b11111111111111111111111111101101 )
1"
#51000
b101 &
b111 %
b111 '
#55000
0"
#60000
b101110 !
b101110 (
b101110 +
b11101 ,
b101 *
b11111111111111111111111111110100 )
1"
#61000
b110 &
#65000
0"
#70000
b1010111 !
b1010111 (
b1010111 +
b110 *
b101110 ,
b11111111111111111111111111111011 )
1"
#71000
b111 &
b11111111111111111111111111111111 %
b11111111111111111111111111111111 '
#75000
0"
#80000
b10101000 !
b10101000 (
b10101000 +
b1010111 ,
b111 *
b11111111111111111111111111111010 )
1"
#81000
b1000 &
b11111111111111111111111111111100 %
b11111111111111111111111111111100 '
#85000
0"
#90000
b101000110 !
b101000110 (
b101000110 +
b1000 *
b10101000 ,
b11111111111111111111111111110110 )
1"
#91000
b1001 &
b1 %
b1 '
#95000
0"
#100000
b1010000011 !
b1010000011 (
b1010000011 +
b101000110 ,
b1001 *
b11111111111111111111111111110111 )
1"
#101000
b1010 &
b1001 %
b1001 '
#105000
0"
#110000
b10100000110 !
b10100000110 (
b10100000110 +
b1010 *
b1010000011 ,
b0 )
1"
#111000
b1011 &
b1000 %
b1000 '
#115000
0"
#120000
b101000010100 !
b101000010100 (
b101000010100 +
b10100000110 ,
b1011 *
b1000 )
1"
#121000
b1100 &
b111 %
b111 '
#125000
0"
#130000
b1010000110111 !
b1010000110111 (
b1010000110111 +
b1100 *
b101000010100 ,
b1111 )
1"
#131000
b1101 &
b1001 %
b1001 '
#135000
0"
#140000
b10100010000110 !
b10100010000110 (
b10100010000110 +
b1010000110111 ,
b1101 *
b11000 )
1"
#141000
b1110 &
b10 %
b10 '
#145000
0"
#150000
b101000100100110 !
b101000100100110 (
b101000100100110 +
b1110 *
b10100010000110 ,
b11010 )
1"
#151000
b1111 &
b1001 %
b1001 '
#155000
0"
#160000
b1010001001101111 !
b1010001001101111 (
b1010001001101111 +
b101000100100110 ,
b1111 *
b100011 )
1"
#161000
b10000 &
b0 %
b0 '
#165000
0"
#170000
b10100010100000001 !
b10100010100000001 (
b10100010100000001 +
b10000 *
b1010001001101111 ,
1"
#171000
b10001 &
b11111111111111111111111111110111 %
b11111111111111111111111111110111 '
#175000
0"
#180000
b101000101000011100 !
b101000101000011100 (
b101000101000011100 +
b10100010100000001 ,
b10001 *
b11010 )
1"
#181000
b10010 &
b11111111111111111111111111111100 %
b11111111111111111111111111111100 '
#185000
0"
#190000
b1010001010001001110 !
b1010001010001001110 (
b1010001010001001110 +
b10010 *
b101000101000011100 ,
b10110 )
1"
#191000
b10011 &
b101 %
b101 '
#195000
0"
#200000
b10100010100010110111 !
b10100010100010110111 (
b10100010100010110111 +
b1010001010001001110 ,
b10011 *
b11011 )
1"
#201000
b10100 &
b11111111111111111111111111111111 %
b11111111111111111111111111111111 '
#205000
0"
#210000
b101000101000110001000 !
b101000101000110001000 (
b101000101000110001000 +
b10100 *
b10100010100010110111 ,
b11010 )
1"
#211000
b10101 &
b11111111111111111111111111111110 %
b11111111111111111111111111111110 '
#215000
0"
#220000
b1010001010001100101000 !
b1010001010001100101000 (
b1010001010001100101000 +
b101000101000110001000 ,
b10101 *
b11000 )
1"
#221000
b10110 &
b1001 %
b1001 '
#225000
0"
#230000
b10100010100011001110001 !
b10100010100011001110001 (
b10100010100011001110001 +
b10110 *
b1010001010001100101000 ,
b100001 )
1"
#231000
b10111 &
b110 %
b110 '
#235000
0"
#240000
b101000101000110100001001 !
b101000101000110100001001 (
b101000101000110100001001 +
b10100010100011001110001 ,
b10111 *
b100111 )
1"
#241000
b11000 &
b11111111111111111111111111111010 %
b11111111111111111111111111111010 '
#245000
0"
#250000
b1010001010001101000110011 !
b1010001010001101000110011 (
b1010001010001101000110011 +
b11000 *
b101000101000110100001001 ,
b100001 )
1"
#251000
b11001 &
b11111111111111111111111111111000 %
b11111111111111111111111111111000 '
#255000
0"
#260000
b10100010100011010001111111 !
b10100010100011010001111111 (
b10100010100011010001111111 +
b1010001010001101000110011 ,
b11001 *
b11001 )
1"
#261000
b11010 &
b11111111111111111111111111111101 %
b11111111111111111111111111111101 '
#265000
0"
#270000
b101000101000110100100010100 !
b101000101000110100100010100 (
b101000101000110100100010100 +
b11010 *
b10100010100011010001111111 ,
b10110 )
1"
#271000
b11011 &
b100 %
b100 '
#275000
0"
#280000
b1010001010001101001001000010 !
b1010001010001101001001000010 (
b1010001010001101001001000010 +
b101000101000110100100010100 ,
b11011 *
b11010 )
1"
#281000
b11100 &
b11111111111111111111111111111101 %
b11111111111111111111111111111101 '
#285000
0"
#290000
b10100010100011010010010011011 !
b10100010100011010010010011011 (
b10100010100011010010010011011 +
b11100 *
b1010001010001101001001000010 ,
b10111 )
1"
#291000
b11101 &
b11111111111111111111111111111001 %
b11111111111111111111111111111001 '
#295000
0"
#300000
b101000101000110100100101000110 !
b101000101000110100100101000110 (
b101000101000110100100101000110 +
b10100010100011010010010011011 ,
b11101 *
b10000 )
1"
#301000
b11110 &
#305000
0"
#310000
b1010001010001101001001010010101 !
b1010001010001101001001010010101 (
b1010001010001101001001010010101 +
b11110 *
b101000101000110100100101000110 ,
b1001 )
1"
#311000
b11111 &
b11111111111111111111111111111101 %
b11111111111111111111111111111101 '
#315000
0"
#320000
b10100010100011010010010100110000 !
b10100010100011010010010100110000 (
b10100010100011010010010100110000 +
b1010001010001101001001010010101 ,
b11111 *
b110 )
1"
#321000
b100000 &
b0 %
b0 '
#325000
0"
#330000
b1000101000110100100101001100110 !
b1000101000110100100101001100110 (
b1000101000110100100101001100110 +
b100000 *
b10100010100011010010010100110000 ,
1"
#331000
b100001 &
b11111111111111111111111111111000 %
b11111111111111111111111111111000 '
#335000
0"
#340000
b10001010001101001001010011001010 !
b10001010001101001001010011001010 (
b10001010001101001001010011001010 +
b1000101000110100100101001100110 ,
b100001 *
b11111111111111111111111111111110 )
1"
#341000
b100010 &
b110 %
b110 '
#345000
0"
#350000
b10100011010010010100110011000 !
b10100011010010010100110011000 (
b10100011010010010100110011000 +
b100010 *
b10001010001101001001010011001010 ,
b100 )
1"
#351000
b100011 &
b100 %
b100 '
#355000
0"
#360000
b101000110100100101001100111000 !
b101000110100100101001100111000 (
b101000110100100101001100111000 +
b10100011010010010100110011000 ,
b100011 *
b1000 )
1"
#361000
b100100 &
b11111111111111111111111111111011 %
b11111111111111111111111111111011 '
#365000
0"
#370000
b1010001101001001010011001110011 !
b1010001101001001010011001110011 (
b1010001101001001010011001110011 +
b100100 *
b101000110100100101001100111000 ,
b11 )
1"
#371000
b100101 &
b11111111111111111111111111111100 %
b11111111111111111111111111111100 '
#375000
0"
#380000
b10100011010010010100110011100101 !
b10100011010010010100110011100101 (
b10100011010010010100110011100101 +
b1010001101001001010011001110011 ,
b100101 *
b11111111111111111111111111111111 )
1"
#381000
b100110 &
b11111111111111111111111111111011 %
b11111111111111111111111111111011 '
#385000
0"
#390000
b1000110100100101001100111000100 !
b1000110100100101001100111000100 (
b1000110100100101001100111000100 +
b100110 *
b10100011010010010100110011100101 ,
b11111111111111111111111111111010 )
1"
#391000
b100111 &
#395000
0"
#400000
b10001101001001010011001101111101 !
b10001101001001010011001101111101 (
b10001101001001010011001101111101 +
b1000110100100101001100111000100 ,
b100111 *
b11111111111111111111111111110101 )
1"
#401000
b101000 &
b11111111111111111111111111111101 %
b11111111111111111111111111111101 '
#405000
0"
#410000
b11010010010100110011011101100 !
b11010010010100110011011101100 (
b11010010010100110011011101100 +
b101000 *
b10001101001001010011001101111101 ,
b11111111111111111111111111110010 )
1"
#411000
b101001 &
b101 %
b101 '
#415000
0"
#420000
b110100100101001100110111001111 !
b110100100101001100110111001111 (
b110100100101001100110111001111 +
b11010010010100110011011101100 ,
b101001 *
b11111111111111111111111111110111 )
1"
#421000
b101010 &
b11111111111111111111111111111111 %
b11111111111111111111111111111111 '
#425000
0"
#430000
b1101001001010011001101110010100 !
b1101001001010011001101110010100 (
b1101001001010011001101110010100 +
b101010 *
b110100100101001100110111001111 ,
b11111111111111111111111111110110 )
1"
#431000
b101011 &
b11111111111111111111111111111000 %
b11111111111111111111111111111000 '
#435000
0"
#440000
b11010010010100110011011100010110 !
b11010010010100110011011100010110 (
b11010010010100110011011100010110 +
b1101001001010011001101110010100 ,
b101011 *
b11111111111111111111111111101110 )
1"
#441000
b101100 &
b11111111111111111111111111111100 %
b11111111111111111111111111111100 '
#445000
0"
#450000
b10100100101001100110111000010110 !
b10100100101001100110111000010110 (
b10100100101001100110111000010110 +
b101100 *
b11010010010100110011011100010110 ,
b11111111111111111111111111101010 )
1"
#451000
b101101 &
b1 %
b1 '
#455000
0"
#460000
b1001001010011001101110000010111 !
b1001001010011001101110000010111 (
b1001001010011001101110000010111 +
b10100100101001100110111000010110 ,
b101101 *
b11111111111111111111111111101011 )
1"
#461000
b101110 &
b11111111111111111111111111111001 %
b11111111111111111111111111111001 '
#465000
0"
#470000
b10010010100110011011100000010010 !
b10010010100110011011100000010010 (
b10010010100110011011100000010010 +
b101110 *
b1001001010011001101110000010111 ,
b11111111111111111111111111100100 )
1"
#471000
b101111 &
b111 %
b111 '
#475000
0"
#480000
b100101001100110111000000001111 !
b100101001100110111000000001111 (
b100101001100110111000000001111 +
b10010010100110011011100000010010 ,
b101111 *
b11111111111111111111111111101011 )
1"
#481000
b110000 &
b0 %
b0 '
#485000
0"
#490000
b1001010011001101110000000001001 !
b1001010011001101110000000001001 (
b1001010011001101110000000001001 +
b110000 *
b100101001100110111000000001111 ,
1"
#491000
b110001 &
#495000
0"
#500000
b10010100110011011011111111111101 !
b10010100110011011011111111111101 (
b10010100110011011011111111111101 +
b1001010011001101110000000001001 ,
b110001 *
1"
#501000
b110010 &
b11111111111111111111111111111000 %
b11111111111111111111111111111000 '
#505000
0"
#510000
b101001100110110111111111011101 !
b101001100110110111111111011101 (
b101001100110110111111111011101 +
b110010 *
b10010100110011011011111111111101 ,
b11111111111111111111111111100011 )
1"
#511000
b110011 &
b110 %
b110 '
#515000
0"
#520000
b1010011001101101111111110100011 !
b1010011001101101111111110100011 (
b1010011001101101111111110100011 +
b101001100110110111111111011101 ,
b110011 *
b11111111111111111111111111101001 )
1"
#521000
b110100 &
b0 %
b0 '
#525000
0"
#530000
b10100110011011011111111100101111 !
b10100110011011011111111100101111 (
b10100110011011011111111100101111 +
b110100 *
b1010011001101101111111110100011 ,
1"
#531000
b110101 &
b111 %
b111 '
#535000
0"
#540000
b1001100110110111111111001001110 !
b1001100110110111111111001001110 (
b1001100110110111111111001001110 +
b10100110011011011111111100101111 ,
b110101 *
b11111111111111111111111111110000 )
1"
#541000
b110110 &
b11111111111111111111111111111110 %
b11111111111111111111111111111110 '
#545000
0"
#550000
b10011001101101111111110010001010 !
b10011001101101111111110010001010 (
b10011001101101111111110010001010 +
b110110 *
b1001100110110111111111001001110 ,
b11111111111111111111111111101110 )
1"
#551000
b110111 &
b0 %
b0 '
#555000
0"
#560000
b110011011011111111100100000010 !
b110011011011111111100100000010 (
b110011011011111111100100000010 +
b10011001101101111111110010001010 ,
b110111 *
1"
#561000
b111000 &
b11111111111111111111111111111001 %
b11111111111111111111111111111001 '
#565000
0"
#570000
b1100110110111111111000111101011 !
b1100110110111111111000111101011 (
b1100110110111111111000111101011 +
b111000 *
b110011011011111111100100000010 ,
b11111111111111111111111111100111 )
1"
#571000
b111001 &
b111 %
b111 '
#575000
0"
#580000
b11001101101111111110001111000100 !
b11001101101111111110001111000100 (
b11001101101111111110001111000100 +
b1100110110111111111000111101011 ,
b111001 *
b11111111111111111111111111101110 )
1"
#581000
b111010 &
b110 %
b110 '
#585000
0"
#590000
b10011011011111111100011101111100 !
b10011011011111111100011101111100 (
b10011011011111111100011101111100 +
b111010 *
b11001101101111111110001111000100 ,
b11111111111111111111111111110100 )
1"
#591000
b111011 &
#595000
0"
#600000
b110110111111111000111011110010 !
b110110111111111000111011110010 (
b110110111111111000111011110010 +
b10011011011111111100011101111100 ,
b111011 *
b11111111111111111111111111111010 )
1"
#601000
b111100 &
#605000
0"
#610000
b1101101111111110001110111100100 !
b1101101111111110001110111100100 (
b1101101111111110001110111100100 +
b111100 *
b110110111111111000111011110010 ,
b0 )
1"
#611000
b111101 &
b11111111111111111111111111111110 %
b11111111111111111111111111111110 '
#615000
0"
#620000
b11011011111111100011101111000110 !
b11011011111111100011101111000110 (
b11011011111111100011101111000110 +
b1101101111111110001110111100100 ,
b111101 *
b11111111111111111111111111111110 )
1"
#621000
b111110 &
b100 %
b100 '
#625000
0"
#630000
b10110111111111000111011110001110 !
b10110111111111000111011110001110 (
b10110111111111000111011110001110 +
b111110 *
b11011011111111100011101111000110 ,
b10 )
1"
#631000
b111111 &
b11111111111111111111111111111101 %
b11111111111111111111111111111101 '
#635000
0"
#640000
b1101111111110001110111100011011 !
b1101111111110001110111100011011 (
b1101111111110001110111100011011 +
b10110111111111000111011110001110 ,
b111111 *
b11111111111111111111111111111111 )
1"
#641000
b1000000 &
#645000
0"
#650000
b11011111111100011101111000110010 !
b11011111111100011101111000110010 (
b11011111111100011101111000110010 +
b1000000 *
b1101111111110001110111100011011 ,
b11111111111111111111111111111100 )
1"
#651000
b1000001 &
b1 %
b1 '
#655000
0"
#660000
b10111111111000111011110001100001 !
b10111111111000111011110001100001 (
b10111111111000111011110001100001 +
b11011111111100011101111000110010 ,
b1000001 *
b11111111111111111111111111111101 )
1"
#661000
b1000010 &
b101 %
b101 '
#665000
0"
#670000
b1111111110001110111100011000100 !
b1111111110001110111100011000100 (
b1111111110001110111100011000100 +
b1000010 *
b10111111111000111011110001100001 ,
b10 )
1"
#671000
b1000011 &
b11111111111111111111111111111011 %
b11111111111111111111111111111011 '
#675000
0"
#680000
b11111111100011101111000110000101 !
b11111111100011101111000110000101 (
b11111111100011101111000110000101 +
b1111111110001110111100011000100 ,
b1000011 *
b11111111111111111111111111111101 )
1"
#681000
b1000100 &
b100 %
b100 '
#685000
0"
#690000
b11111111000111011110001100001011 !
b11111111000111011110001100001011 (
b11111111000111011110001100001011 +
b1000100 *
b11111111100011101111000110000101 ,
b1 )
1"
#691000
b1000101 &
b11111111111111111111111111111100 %
b11111111111111111111111111111100 '
#695000
0"
#700000
b11111110001110111100011000010011 !
b11111110001110111100011000010011 (
b11111110001110111100011000010011 +
b11111111000111011110001100001011 ,
b1000101 *
b11111111111111111111111111111101 )
1"
#701000
b1000110 &
b1 %
b1 '
#705000
0"
#710000
b11111100011101111000110000100100 !
b11111100011101111000110000100100 (
b11111100011101111000110000100100 +
b1000110 *
b11111110001110111100011000010011 ,
b11111111111111111111111111111110 )
1"
#711000
b1000111 &
b11 %
b11 '
#715000
0"
#720000
b11111000111011110001100001001001 !
b11111000111011110001100001001001 (
b11111000111011110001100001001001 +
b11111100011101111000110000100100 ,
b1000111 *
b1 )
1"
#721000
b1001000 &
b1 %
b1 '
#725000
0"
#730000
b11110001110111100011000010010100 !
b11110001110111100011000010010100 (
b11110001110111100011000010010100 +
b1001000 *
b11111000111011110001100001001001 ,
b10 )
1"
#731000
b1001001 &
b100 %
b100 '
#735000
0"
#740000
b11100011101111000110000100101110 !
b11100011101111000110000100101110 (
b11100011101111000110000100101110 +
b11110001110111100011000010010100 ,
b1001001 *
b110 )
1"
#741000
b1001010 &
b1000 %
b1000 '
#745000
0"
#750000
b11000111011110001100001001101010 !
b11000111011110001100001001101010 (
b11000111011110001100001001101010 +
b1001010 *
b11100011101111000110000100101110 ,
b1110 )
1"
#751000
b1001011 &
b1001 %
b1001 '
#755000
0"
#760000
b10001110111100011000010011101011 !
b10001110111100011000010011101011 (
b10001110111100011000010011101011 +
b11000111011110001100001001101010 ,
b1001011 *
b10111 )
1"
#761000
b1001100 &
b101 %
b101 '
#765000
0"
#770000
b11101111000110000100111110010 !
b11101111000110000100111110010 (
b11101111000110000100111110010 +
b1001100 *
b10001110111100011000010011101011 ,
b11100 )
1"
#771000
b1001101 &
b0 %
b0 '
#775000
0"
#780000
b111011110001100001010000000000 !
b111011110001100001010000000000 (
b111011110001100001010000000000 +
b11101111000110000100111110010 ,
b1001101 *
1"
#781000
b1001110 &
b11111111111111111111111111111101 %
b11111111111111111111111111111101 '
#785000
0"
#790000
b1110111100011000010100000011001 !
b1110111100011000010100000011001 (
b1110111100011000010100000011001 +
b1001110 *
b111011110001100001010000000000 ,
b11001 )
1"
#791000
b1001111 &
#795000
0"
#800000
b11101111000110000101000001001000 !
b11101111000110000101000001001000 (
b11101111000110000101000001001000 +
b1110111100011000010100000011001 ,
b1001111 *
b10110 )
1"
#801000
b1010000 &
b11111111111111111111111111111110 %
b11111111111111111111111111111110 '
#805000
0"
#810000
b11011110001100001010000010100100 !
b11011110001100001010000010100100 (
b11011110001100001010000010100100 +
b1010000 *
b11101111000110000101000001001000 ,
b10100 )
1"
#811000
b1010001 &
b11111111111111111111111111111001 %
b11111111111111111111111111111001 '
#815000
0"
#820000
b10111100011000010100000101010101 !
b10111100011000010100000101010101 (
b10111100011000010100000101010101 +
b11011110001100001010000010100100 ,
b1010001 *
b1101 )
1"
#821000
b1010010 &
b111 %
b111 '
#825000
0"
#830000
b1111000110000101000001010111110 !
b1111000110000101000001010111110 (
b1111000110000101000001010111110 +
b1010010 *
b10111100011000010100000101010101 ,
b10100 )
1"
#831000
b1010011 &
b11111111111111111111111111111011 %
b11111111111111111111111111111011 '
#835000
0"
#840000
b11110001100001010000010110001011 !
b11110001100001010000010110001011 (
b11110001100001010000010110001011 +
b1111000110000101000001010111110 ,
b1010011 *
b1111 )
1"
#841000
b1010100 &
b11111111111111111111111111111100 %
b11111111111111111111111111111100 '
#845000
0"
#850000
b11100011000010100000101100100001 !
b11100011000010100000101100100001 (
b11100011000010100000101100100001 +
b1010100 *
b11110001100001010000010110001011 ,
b1011 )
1"
#851000
b1010101 &
b11111111111111111111111111111011 %
b11111111111111111111111111111011 '
#855000
0"
#860000
b11000110000101000001011001001000 !
b11000110000101000001011001001000 (
b11000110000101000001011001001000 +
b11100011000010100000101100100001 ,
b1010101 *
b110 )
1"
#861000
b1010110 &
b11111111111111111111111111111111 %
b11111111111111111111111111111111 '
#865000
0"
#870000
b10001100001010000010110010010101 !
b10001100001010000010110010010101 (
b10001100001010000010110010010101 +
b1010110 *
b11000110000101000001011001001000 ,
b101 )
1"
#871000
b1010111 &
b0 %
b0 '
#875000
0"
#880000
b11000010100000101100100101111 !
b11000010100000101100100101111 (
b11000010100000101100100101111 +
b10001100001010000010110010010101 ,
b1010111 *
1"
#881000
b1011000 &
b100 %
b100 '
#885000
0"
#890000
b110000101000001011001001100111 !
b110000101000001011001001100111 (
b110000101000001011001001100111 +
b1011000 *
b11000010100000101100100101111 ,
b1001 )
1"
#891000
b1011001 &
b11111111111111111111111111111110 %
b11111111111111111111111111111110 '
#895000
0"
#900000
b1100001010000010110010011010101 !
b1100001010000010110010011010101 (
b1100001010000010110010011010101 +
b110000101000001011001001100111 ,
b1011001 *
b111 )
1"
#901000
b1011010 &
b100 %
b100 '
#905000
0"
#910000
b11000010100000101100100110110101 !
b11000010100000101100100110110101 (
b11000010100000101100100110110101 +
b1011010 *
b1100001010000010110010011010101 ,
b1011 )
1"
#911000
b1011011 &
b11111111111111111111111111111011 %
b11111111111111111111111111111011 '
#915000
0"
#920000
b10000101000001011001001101110000 !
b10000101000001011001001101110000 (
b10000101000001011001001101110000 +
b11000010100000101100100110110101 ,
b1011011 *
b110 )
1"
#921000
b1011100 &
b101 %
b101 '
#925000
0"
#930000
b1010000010110010011011101011 !
b1010000010110010011011101011 (
b1010000010110010011011101011 +
b1011100 *
b10000101000001011001001101110000 ,
b1011 )
1"
#931000
b1011101 &
b1000 %
b1000 '
#935000
0"
#940000
b10100000101100100110111101001 !
b10100000101100100110111101001 (
b10100000101100100110111101001 +
b1010000010110010011011101011 ,
b1011101 *
b10011 )
1"
#941000
b1011110 &
b11111111111111111111111111111100 %
b11111111111111111111111111111100 '
#945000
0"
#950000
b101000001011001001101111100001 !
b101000001011001001101111100001 (
b101000001011001001101111100001 +
b1011110 *
b10100000101100100110111101001 ,
b1111 )
1"
#951000
b1011111 &
b1 %
b1 '
#955000
0"
#960000
b1010000010110010011011111010010 !
b1010000010110010011011111010010 (
b1010000010110010011011111010010 +
b101000001011001001101111100001 ,
b1011111 *
b10000 )
1"
#961000
b1100000 &
b11 %
b11 '
#965000
0"
#970000
b10100000101100100110111110110111 !
b10100000101100100110111110110111 (
b10100000101100100110111110110111 +
b1100000 *
b1010000010110010011011111010010 ,
b10011 )
1"
#971000
b1100001 &
b1001 %
b1001 '
#975000
0"
#980000
b1000001011001001101111110001010 !
b1000001011001001101111110001010 (
b1000001011001001101111110001010 +
b10100000101100100110111110110111 ,
b1100001 *
b11100 )
1"
#981000
b1100010 &
b11111111111111111111111111111111 %
b11111111111111111111111111111111 '
#985000
0"
#990000
b10000010110010011011111100101111 !
b10000010110010011011111100101111 (
b10000010110010011011111100101111 +
b1100010 *
b1000001011001001101111110001010 ,
b11011 )
1"
#991000
b1100011 &
b11 %
b11 '
#995000
0"
#1000000
b101100100110111111001111100 !
b101100100110111111001111100 (
b101100100110111111001111100 +
b10000010110010011011111100101111 ,
b1100011 *
b11110 )
1"
#1001000
b1100100 &
b11111111111111111111111111111110 %
b11111111111111111111111111111110 '
#1005000
0"
#1010000
b101100100110111111001111010 !
b101100100110111111001111010 (
b101100100110111111001111010 +
b11100 )
1"
#1015000
0"
#1020000
b101100100110111111001111000 !
b101100100110111111001111000 (
b101100100110111111001111000 +
b11010 )
1"
#1025000
0"
#1030000
b101100100110111111001110110 !
b101100100110111111001110110 (
b101100100110111111001110110 +
b11000 )
1"
#1035000
0"
#1040000
b101100100110111111001110100 !
b101100100110111111001110100 (
b101100100110111111001110100 +
b10110 )
1"
#1045000
0"
#1050000
b101100100110111111001110010 !
b101100100110111111001110010 (
b101100100110111111001110010 +
b10100 )
1"
#1055000
0"
#1060000
b101100100110111111001110000 !
b101100100110111111001110000 (
b101100100110111111001110000 +
b10010 )
1"
#1065000
0"
#1070000
b101100100110111111001101110 !
b101100100110111111001101110 (
b101100100110111111001101110 +
b10000 )
1"
#1075000
0"
#1080000
b101100100110111111001101100 !
b101100100110111111001101100 (
b101100100110111111001101100 +
b1110 )
1"
#1085000
0"
#1090000
b101100100110111111001101010 !
b101100100110111111001101010 (
b101100100110111111001101010 +
b1100 )
1"
#1095000
0"
#1100000
b101100100110111111001101000 !
b101100100110111111001101000 (
b101100100110111111001101000 +
b1010 )
1"
#1105000
0"
#1110000
b101100100110111111001100110 !
b101100100110111111001100110 (
b101100100110111111001100110 +
b1000 )
1"
