circuit.v
`timescale 1ns / 1ps
`include "iob_lib.vh"

`define W = 32
module circuit
  #(
    parameter W = 32
    )
  (
   `INPUT(rst,1),
   `INPUT(clk,1),
   `INPUT(en,1),
   `INPUT(x,W),
   `OUTPUT(y,W)
   );
   `SIGNAL(cnt, 7)
   `SIGNAL(y_final, W)
   `SIGNAL(y_final_1, W)
   `SIGNAL2OUT(y, y_final)


   `REG_RE(clk, rst, 1'b0, en & (cnt!=99), y_final_1, y_final)
   `COUNTER_RE(clk, rst, en & (cnt!=99), cnt)
   `COMB y_final = y_final_1 + y_final_1 + x + (cnt == 1'b1);
endmodule

circuit_tb.v
`timescale 1ns / 1ps
`include "iob_lib.vh"

`define W 32

module circuit_tb;

   `CLOCK(clk, 10)
   `RESET(rst, 1, 10)
   `SIGNAL(en, 1)
   `SIGNAL(x, `W)
   `SIGNAL_OUT(y, `W)

   integer i;

   initial begin
      $dumpfile("circuit.vcd");
      $dumpvars();
      en=0;
      x=$random;
      for (i=0; i<100; i=i+1) begin
         @(posedge clk) #1 x=$random; en=1;
         $display("%d: %d",i+1, y);
      end

      @(posedge clk) #100 $finish;

   end

   circuit
     #(
       .W(`W)
       )
   c0
     (
      .rst(rst),
      .clk(clk),
      .en(en),
      .x(x),
      .y(y)
      );


endmodule

circuit.vcd
$date
	Tue Nov 17 21:23:51 2020
$end
$version
	Icarus Verilog
$end
$timescale
	1ps
$end
$scope module circuit_tb $end
$var wire 32 ! y [31:0] $end
$var reg 1 " clk $end
$var reg 1 # en $end
$var reg 1 $ rst $end
$var reg 32 % x [31:0] $end
$var integer 32 & i [31:0] $end
$scope module c0 $end
$var wire 1 " clk $end
$var wire 1 # en $end
$var wire 1 $ rst $end
$var wire 32 ' x [31:0] $end
$var wire 32 ( y [31:0] $end
$var reg 7 ) cnt [6:0] $end
$var reg 32 * y_final [31:0] $end
$var reg 32 + y_final_1 [31:0] $end
$upscope $end
$upscope $end
$enddefinitions $end
#0
$dumpvars
bx +
bx *
bx )
bx (
b10010000101010011010100100100 '
b0 &
b10010000101010011010100100100 %
0$
0#
1"
bx !
$end
#1000
1$
#5000
0"
#10000
b10010000101010011010100100100 !
b10010000101010011010100100100 (
b10010000101010011010100100100 *
b0 )
b0 +
1"
#11000
b11000000100010010101111010000001 !
b11000000100010010101111010000001 (
b11000000100010010101111010000001 *
b1 &
1#
b11000000100010010101111010000001 %
b11000000100010010101111010000001 '
0$
#15000
0"
#20000
b1000001100111000001101110000100 !
b1000001100111000001101110000100 (
b1000001100111000001101110000100 *
b11000000100010010101111010000001 +
b1 )
1"
#21000
b101100101111001001100001100 !
b101100101111001001100001100 (
b101100101111001001100001100 *
b10 &
b10000100100001001101011000001001 %
b10000100100001001101011000001001 '
#25000
0"
#30000
b10001111101100111111110000100001 !
b10001111101100111111110000100001 (
b10001111101100111111110000100001 *
b10 )
b101100101111001001100001100 +
1"
#31000
b10111101000111110111110001111011 !
b10111101000111110111110001111011 (
b10111101000111110111110001111011 *
b11 &
b10110001111100000101011001100011 %
b10110001111100000101011001100011 '
#35000
0"
#40000
b101100001011110100111101011001 !
b101100001011110100111101011001 (
b101100001011110100111101011001 *
b10111101000111110111110001111011 +
b11 )
1"
#41000
b10000000111110000111010000000011 !
b10000000111110000111010000000011 (
b10000000111110000111010000000011 *
b100 &
b110101110010111101100001101 %
b110101110010111101100001101 '
#45000
0"
#50000
b1000101010100110001100010011 !
b1000101010100110001100010011 (
b1000101010100110001100010011 *
b100 )
b10000000111110000111010000000011 +
1"
#51000
b1001000110100001000000110010011 !
b1001000110100001000000110010011 (
b1001000110100001000000110010011 *
b101 &
b1000110110111111001100110001101 %
b1000110110111111001100110001101 '
#55000
0"
#60000
b11011000100000001001110010110011 !
b11011000100000001001110010110011 (
b11011000100000001001110010110011 *
b1001000110100001000000110010011 +
b101 )
1"
#61000
b1000100011000111000011110001011 !
b1000100011000111000011110001011 (
b1000100011000111000011110001011 *
b110 &
b10110010110000101000010001100101 %
b10110010110000101000010001100101 '
#65000
0"
#70000
b111011100010011001001101111011 !
b111011100010011001001101111011 (
b111011100010011001001101111011 *
b110 )
b1000100011000111000011110001011 +
1"
#71000
b10001111111100110000100101000 !
b10001111111100110000100101000 (
b10001111111100110000100101000 *
b111 &
b10001001001101110101001000010010 %
b10001001001101110101001000010010 '
#75000
0"
#80000
b10101101001101000001010001100010 !
b10101101001101000001010001100010 (
b10101101001101000001010001100010 *
b10001111111100110000100101000 +
b111 )
1"
#81000
b100100111100001010010101010001 !
b100100111100001010010101010001 (
b100100111100001010010101010001 *
b1000 &
b111100111110001100000001 %
b111100111110001100000001 '
#85000
0"
#90000
b1001010110101010010110110100011 !
b1001010110101010010110110100011 (
b1001010110101010010110110100011 *
b1000 )
b100100111100001010010101010001 +
1"
#91000
b1010000101110010001011110101111 !
b1010000101110010001011110101111 (
b1010000101110010001011110101111 *
b1001 &
b110110101111100110100001101 %
b110110101111100110100001101 '
#95000
0"
#100000
b10101000010010011111110001101011 !
b10101000010010011111110001101011 (
b10101000010010011111110001101011 *
b1010000101110010001011110101111 +
b1001 )
1"
#101000
b11011100100101100010000011010100 !
b11011100100101100010000011010100 (
b11011100100101100010000011010100 *
b1010 &
b111011001000111111000101110110 %
b111011001000111111000101110110 '
#105000
0"
#110000
b11110100010100000011001100011110 !
b11110100010100000011001100011110 (
b11110100010100000011001100011110 *
b1010 )
b11011100100101100010000011010100 +
1"
#111000
b11010111101110100000111011100101 !
b11010111101110100000111011100101 (
b11010111101110100000111011100101 *
b1011 &
b11110100011011100110100111101 %
b11110100011011100110100111101 '
#115000
0"
#120000
b11001110000000011110101100000111 !
b11001110000000011110101100000111 (
b11001110000000011110101100000111 *
b11010111101110100000111011100101 +
b1011 )
1"
#121000
b100110010010000111010110110111 !
b100110010010000111010110110111 (
b100110010010000111010110110111 *
b1100 &
b1110110110101000101011111101101 %
b1110110110101000101011111101101 '
#125000
0"
#130000
b11000011011001010100001101011011 !
b11000011011001010100001101011011 (
b11000011011001010100001101011011 *
b1100 )
b100110010010000111010110110111 +
1"
#131000
b10010010101111101110001011111010 !
b10010010101111101110001011111010 (
b10010010101111101110001011111010 *
b1101 &
b1000110001011011111011110001100 %
b1000110001011011111011110001100 '
#135000
0"
#140000
b1101011101010111011110110000000 !
b1101011101010111011110110000000 (
b1101011101010111011110110000000 *
b10010010101111101110001011111010 +
b1101 )
1"
#141000
b10100010011110111010111111101101 !
b10100010011110111010111111101101 (
b10100010011110111010111111101101 *
b1110 &
b1111100111111011110100111111001 %
b1111100111111011110100111111001 '
#145000
0"
#150000
b11000001111101010100100111010011 !
b11000001111101010100100111010011 (
b11000001111101010100100111010011 *
b1110 )
b10100010011110111010111111101101 +
1"
#151000
b101000001011101000010010100000 !
b101000001011101000010010100000 (
b101000001011101000010010100000 *
b1111 &
b11100011001101110010010011000110 %
b11100011001101110010010011000110 '
#155000
0"
#160000
b110011100101000010111000000110 !
b110011100101000010111000000110 (
b110011100101000010111000000110 *
b101000001011101000010010100000 +
b1111 )
1"
#161000
b110011010101001000111000000101 !
b110011010101001000111000000101 (
b110011010101001000111000000101 *
b10000 &
b11100010111101111000010011000101 %
b11100010111101111000010011000101 '
#165000
0"
#170000
b1001001101000001010000011001111 !
b1001001101000001010000011001111 (
b1001001101000001010000011001111 *
b10000 )
b110011010101001000111000000101 +
1"
#171000
b111011101111001110111010110100 !
b111011101111001110111010110100 (
b111011101111001110111010110100 *
b10001 &
b11010101000100111101001010101010 %
b11010101000100111101001010101010 '
#175000
0"
#180000
b1001100100011011011000000010010 !
b1001100100011011011000000010010 (
b1001100100011011011000000010010 *
b111011101111001110111010110100 +
b10001 )
1"
#181000
b11101010001010011101010101001101 !
b11101010001010011101010101001101 (
b11101010001010011101010101001101 *
b10010 &
b1110010101011111111011111100101 %
b1110010101011111111011111100101 '
#185000
0"
#190000
b1000111000000111010001001111111 !
b1000111000000111010001001111111 (
b1000111000000111010001001111111 *
b10010 )
b11101010001010011101010101001101 +
1"
#191000
b10010000001001100001110100010001 !
b10010000001001100001110100010001 (
b10010000001001100001110100010001 *
b10011 &
b10111011110100100111001001110111 %
b10111011110100100111001001110111 '
#195000
0"
#200000
b11011100000111101010110010011001 !
b11011100000111101010110010011001 (
b11011100000111101010110010011001 *
b10010000001001100001110100010001 +
b10011 )
1"
#201000
b10101001011111110001000000110100 !
b10101001011111110001000000110100 (
b10101001011111110001000000110100 *
b10100 &
b10001001001100101101011000010010 %
b10001001001100101101011000010010 '
#205000
0"
#210000
b11011100001100001111011001111010 !
b11011100001100001111011001111010 (
b11011100001100001111011001111010 *
b10100 )
b10101001011111110001000000110100 +
1"
#211000
b10011010111010101111101111110111 !
b10011010111010101111101111110111 (
b10011010111010101111101111110111 *
b10101 &
b1000111111011001101101110001111 %
b1000111111011001101101110001111 '
#215000
0"
#220000
b1111101110000101101001101111101 !
b1111101110000101101001101111101 (
b1111101110000101101001101111101 *
b10011010111010101111101111110111 +
b10101 )
1"
#221000
b10101111000001100110000111100000 !
b10101111000001100110000111100000 (
b10101111000001100110000111100000 *
b10110 &
b1111001001100000110100111110010 %
b1111001001100000110100111110010 '
#225000
0"
#230000
b11010111001111010010110110110010 !
b11010111001111010010110110110010 (
b11010111001111010010110110110010 *
b10110 )
b10101111000001100110000111100000 +
1"
#231000
b1000101100000110101101010001110 !
b1000101100000110101101010001110 (
b1000101100000110101101010001110 *
b10111 &
b11100111011101101001011011001110 %
b11100111011101101001011011001110 '
#235000
0"
#240000
b1110010011111010100101111101010 !
b1110010011111010100101111101010 (
b1110010011111010100101111101010 *
b1000101100000110101101010001110 +
b10111 )
1"
#241000
b1111111000001110011000000000100 !
b1111111000001110011000000000100 (
b1111111000001110011000000000100 *
b11000 &
b11110100000000000111101011101000 %
b11110100000000000111101011101000 '
#245000
0"
#250000
b11110010000011101101101011110000 !
b11110010000011101101101011110000 (
b11110010000011101101101011110000 *
b11000 )
b1111111000001110011000000000100 +
1"
#251000
b11100000110110001010111011001101 !
b11100000110110001010111011001101 (
b11100000110110001010111011001101 *
b11001 &
b11100010110010100100111011000101 %
b11100010110010100100111011000101 '
#255000
0"
#260000
b10100100011110111010110001011111 !
b10100100011110111010110001011111 (
b10100100011110111010110001011111 *
b11100000110110001010111011001101 +
b11001 )
1"
#261000
b11110000000010011010011011110110 !
b11110000000010011010011011110110 (
b11110000000010011010011011110110 *
b11010 &
b101110010110000100100101011100 %
b101110010110000100100101011100 '
#265000
0"
#270000
b1110011010111001011101001000 !
b1110011010111001011101001000 (
b1110011010111001011101001000 *
b11010 )
b11110000000010011010011011110110 +
1"
#271000
b10111110101000010111011010101001 !
b10111110101000010111011010101001 (
b10111110101000010111011010101001 *
b11011 &
b11011110100011100010100010111101 %
b11011110100011100010100010111101 '
#275000
0"
#280000
b1011011110100010001011000001111 !
b1011011110100010001011000001111 (
b1011011110100010001011000001111 *
b10111110101000010111011010101001 +
b11011 )
1"
#281000
b10011111011100100010101111111 !
b10011111011100100010101111111 (
b10011111011100100010101111111 *
b11100 &
b10010110101010110101100000101101 %
b10010110101010110101100000101101 '
#285000
0"
#290000
b10111110100001111110001100101011 !
b10111110100001111110001100101011 (
b10111110100001111110001100101011 *
b11100 )
b10011111011100100010101111111 +
1"
#291000
b11011010100000111011000101100011 !
b11011010100000111011000101100011 (
b11011010100000111011000101100011 *
b11101 &
b10110010101001110010011001100101 %
b10110010101001110010011001100101 '
#295000
0"
#300000
b1100111101011101000100100101011 !
b1100111101011101000100100101011 (
b1100111101011101000100100101011 *
b11011010100000111011000101100011 +
b11101 )
1"
#301000
b1100110111101101100010100101001 !
b1100110111101101100010100101001 (
b1100110111101101100010100101001 *
b11110 &
b10110001111011110110001001100011 %
b10110001111011110110001001100011 '
#305000
0"
#310000
b1111111110111001110110010110101 !
b1111111110111001110110010110101 (
b1111111110111001110110010110101 *
b11110 )
b1100110111101101100010100101001 +
1"
#311000
b11010011011000010001000101011100 !
b11010011011000010001000101011100 (
b11010011011000010001000101011100 *
b11111 &
b101011100111000011100001010 %
b101011100111000011100001010 '
#315000
0"
#320000
b10101100001101011010100111000010 !
b10101100001101011010100111000010 (
b10101100001101011010100111000010 *
b11010011011000010001000101011100 +
b11111 )
1"
#321000
b1100110111111010100010100111000 !
b1100110111111010100010100111000 (
b1100110111111010100010100111000 *
b100000 &
b11000000001110110010001010000000 %
b11000000001110110010001010000000 '
#325000
0"
#330000
b10001110001101011010110011110000 !
b10001110001101011010110011110000 (
b10001110001101011010110011110000 *
b100000 )
b1100110111111010100010100111000 +
1"
#331000
b11011110010111101010101110010000 !
b11011110010111101010101110010000 (
b11011110010111101010101110010000 *
b100001 &
b10000011001000010000100100000 %
b10000011001000010000100100000 '
#335000
0"
#340000
b11001101001000010111100001000000 !
b11001101001000010111100001000000 (
b11001101001000010111100001000000 *
b11011110010111101010101110010000 +
b100001 )
1"
#341000
b10010001101011001110011001010 !
b10010001101011001110011001010 (
b10010001101011001110011001010 *
b100010 &
b1010101011110000100010110101010 %
b1010101011110000100010110101010 '
#345000
0"
#350000
b1111001111000110111111100111110 !
b1111001111000110111111100111110 (
b1111001111000110111111100111110 *
b100010 )
b10010001101011001110011001010 +
1"
#351000
b11110011001110000000011000110001 !
b11110011001110000000011000110001 (
b11110011001110000000011000110001 *
b100011 &
b11001110110011001100110010011101 %
b11001110110011001100110010011101 '
#355000
0"
#360000
b10110101001111001101100011111111 !
b10110101001111001101100011111111 (
b10110101001111001101100011111111 *
b11110011001110000000011000110001 +
b100011 )
1"
#361000
b10110001100100000100101011111000 !
b10110001100100000100101011111000 (
b10110001100100000100101011111000 *
b100100 &
b11001011001000000011111010010110 %
b11001011001000000011111010010110 '
#365000
0"
#370000
b101110010000001101010010000110 !
b101110010000001101010010000110 (
b101110010000001101010010000110 *
b100100 )
b10110001100100000100101011111000 +
1"
#371000
b11101100101001000100111000000011 !
b11101100101001000100111000000011 (
b11101100101001000100111000000011 *
b100101 &
b10001001100000111011100000010011 %
b10001001100000111011100000010011 '
#375000
0"
#380000
b1100010110011000101010000011001 !
b1100010110011000101010000011001 (
b1100010110011000101010000011001 *
b11101100101001000100111000000011 +
b100101 )
1"
#381000
b1100000000001001101010000010011 !
b1100000000001001101010000010011 (
b1100000000001001101010000010011 *
b100110 &
b10000110101111000011100000001101 %
b10000110101111000011100000001101 '
#385000
0"
#390000
b1000110110001011110000000110011 !
b1000110110001011110000000110011 (
b1000110110001011110000000110011 *
b100110 )
b1100000000001001101010000010011 +
1"
#391000
b1101001101100010111111001111001 !
b1101001101100010111111001111001 (
b1101001101100010111111001111001 *
b100111 &
b10101001101001111101011001010011 %
b10101001101001111101011001010011 '
#395000
0"
#400000
b1111101000010101101001101000101 !
b1111101000010101101001101000101 (
b1111101000010101101001101000101 *
b1101001101100010111111001111001 +
b100111 )
1"
#401000
b1001000000101101101001011101 !
b1001000000101101101001011101 (
b1001000000101101101001011101 *
b101000 &
b110101100111111101110101101011 %
b110101100111111101110101101011 '
#405000
0"
#410000
b1000111101001011001001000100101 !
b1000111101001011001001000100101 (
b1000111101001011001001000100101 *
b101000 )
b1001000000101101101001011101 +
1"
#411000
b11111100101010111101111110001111 !
b11111100101010111101111110001111 (
b11111100101010111101111110001111 *
b101001 &
b11101010101001100010101011010101 %
b11101010101001100010101011010101 '
#415000
0"
#420000
b11100011111111011110100111110011 !
b11100011111111011110100111110011 (
b11100011111111011110100111110011 *
b11111100101010111101111110001111 +
b101001 )
1"
#421000
b1111010011011110000100100100000 !
b1111010011011110000100100100000 (
b1111010011011110000100100100000 *
b101010 &
b10000001000101110100101000000010 %
b10000001000101110100101000000010 '
#425000
0"
#430000
b1110101111101010101110001000010 !
b1110101111101010101110001000010 (
b1110101111101010101110001000010 *
b101010 )
b1111010011011110000100100100000 +
1"
#431000
b11001100001101000101000011101110 !
b11001100001101000101000011101110 (
b11001100001101000101000011101110 *
b101011 &
b11010111010101100011111010101110 %
b11010111010101100011111010101110 '
#435000
0"
#440000
b1101111101111101110000010001010 !
b1101111101111101110000010001010 (
b1101111101111101110000010001010 *
b11001100001101000101000011101110 +
b101011 )
1"
#441000
b10100111011010001000101011111001 !
b10100111011010001000101011111001 (
b10100111011010001000101011111001 *
b101100 &
b1110111111111110100100011101 %
b1110111111111110100100011101 '
#445000
0"
#450000
b1011101110100001111111100001111 !
b1011101110100001111111100001111 (
b1011101110100001111111100001111 *
b101100 )
b10100111011010001000101011111001 +
1"
#451000
b110110100101101000100011000001 !
b110110100101101000100011000001 (
b110110100101101000100011000001 *
b101101 &
b11100111110001010111001011001111 %
b11100111110001010111001011001111 '
#455000
0"
#460000
b1010100111100101000010001010001 !
b1010100111100101000010001010001 (
b1010100111100101000010001010001 *
b110110100101101000100011000001 +
b101101 )
1"
#461000
b1111110101100010101101010100101 !
b1111110101100010101101010100101 (
b1111110101100010101101010100101 *
b101110 &
b10001100001000100100100100011 %
b10001100001000100100100100011 '
#465000
0"
#470000
b1110111001101111111001101101 !
b1110111001101111111001101101 (
b1110111001101111111001101101 *
b101110 )
b1111110101100010101101010100101 +
1"
#471000
b10011011000001101001010100 !
b10011011000001101001010100 (
b10011011000001101001010100 *
b101111 &
b101000010010110010100001010 %
b101000010010110010100001010 '
#475000
0"
#480000
b1001111000011001100110110010 !
b1001111000011001100110110010 (
b1001111000011001100110110010 *
b10011011000001101001010100 +
b101111 )
1"
#481000
b11101010010010110011111101110010 !
b11101010010010110011111101110010 (
b11101010010010110011111101110010 *
b110000 &
b11100101011100110000101011001010 %
b11100101011100110000101011001010 '
#485000
0"
#490000
b10111010000010011000100110101110 !
b10111010000010011000100110101110 (
b10111010000010011000100110101110 *
b110000 )
b11101010010010110011111101110010 +
1"
#491000
b1110010110001111100101100100000 !
b1110010110001111100101100100000 (
b1110010110001111100101100100000 *
b110001 &
b10011110001100010100110000111100 %
b10011110001100010100110000111100 '
#495000
0"
#500000
b10000011110000001110001001111100 !
b10000011110000001110001001111100 (
b10000011110000001110001001111100 *
b1110010110001111100101100100000 +
b110001 )
1"
#501000
b1011110111110000101010000110010 !
b1011110111110000101010000110010 (
b1011110111110000101010000110010 *
b110010 &
b1111001011010001011110111110010 %
b1111001011010001011110111110010 '
#505000
0"
#510000
b110111010110010110011001010110 !
b110111010110010110011001010110 (
b110111010110010110011001010110 *
b110010 )
b1011110111110000101010000110010 +
1"
#511000
b11000111110000100111101110 !
b11000111110000100111101110 (
b11000111110000100111101110 *
b110011 &
b1000101001011100110000110001010 %
b1000101001011100110000110001010 '
#515000
0"
#520000
b1001011011011000111010101100110 !
b1001011011011000111010101100110 (
b1001011011011000111010101100110 *
b11000111110000100111101110 +
b110011 )
1"
#521000
b100111000000101100011100011101 !
b100111000000101100011100011101 (
b100111000000101100011100011101 *
b110100 &
b100000110001001011001101000001 %
b100000110001001011001101000001 '
#525000
0"
#530000
b1101110110010100100000101111011 !
b1101110110010100100000101111011 (
b1101110110010100100000101111011 *
b110100 )
b100111000000101100011100011101 +
1"
#531000
b111010010100001100001100010010 !
b111010010100001100001100010010 (
b111010010100001100001100010010 *
b110101 &
b11101100010010110011010011011000 %
b11101100010010110011010011011000 '
#535000
0"
#540000
b1100000111011001011101011111100 !
b1100000111011001011101011111100 (
b1100000111011001011101011111100 *
b111010010100001100001100010010 +
b110101 )
1"
#541000
b10110000110000100111100110011100 !
b10110000110000100111100110011100 (
b10110000110000100111100110011100 *
b110110 &
b111100001000001111001101111000 %
b111100001000001111001101111000 '
#545000
0"
#550000
b10011101101001011110011010110000 !
b10011101101001011110011010110000 (
b10011101101001011110011010110000 *
b110110 )
b10110000110000100111100110011100 +
1"
#551000
b100110000011110000010111000001 !
b100110000011110000010111000001 (
b100110000011110000010111000001 *
b110111 &
b11000100100010100001001010001001 %
b11000100100010100001001010001001 '
#555000
0"
#560000
b10000101010000001111000001011 !
b10000101010000001111000001011 (
b10000101010000001111000001011 *
b100110000011110000010111000001 +
b110111 )
1"
#561000
b11000001111000110001100101101101 !
b11000001111000110001100101101101 (
b11000001111000110001100101101101 *
b111000 &
b1110101110001010000110111101011 %
b1110101110001010000110111101011 '
#565000
0"
#570000
b11111001100010110100000011000101 !
b11111001100010110100000011000101 (
b11111001100010110100000011000101 *
b111000 )
b11000001111000110001100101101101 +
1"
#571000
b11011110110010001001100010010000 !
b11011110110010001001100010010000 (
b11011110110010001001100010010000 *
b111001 &
b1011011000000100110010110110110 %
b1011011000000100110010110110110 '
#575000
0"
#580000
b11000100100111001011011010110 !
b11000100100111001011011010110 (
b11000100100111001011011010110 *
b11011110110010001001100010010000 +
b111001 )
1"
#581000
b100000110111010010101011100110 !
b100000110111010010101011100110 (
b100000110111010010101011100110 *
b111010 &
b1100011010010111111100111000110 %
b1100011010010111111100111000110 '
#585000
0"
#590000
b10100101000001100100111110010010 !
b10100101000001100100111110010010 (
b10100101000001100100111110010010 *
b111010 )
b100000110111010010101011100110 +
1"
#591000
b10011000110011110110100101111010 !
b10011000110011110110100101111010 (
b10011000110011110110100101111010 *
b111011 &
b1010111000101010001001110101110 %
b1010111000101010001001110101110 '
#595000
0"
#600000
b10001000101100111110011010100010 !
b10001000101100111110011010100010 (
b10001000101100111110011010100010 *
b10011000110011110110100101111010 +
b111011 )
1"
#601000
b10000000100111101010110110000 !
b10000000100111101010110110000 (
b10000000100111101010110110000 *
b111100 &
b11011110011101010000001010111100 %
b11011110011101010000001010111100 '
#605000
0"
#610000
b11111110100111001010111000011100 !
b11111110100111001010111000011100 (
b11111110100111001010111000011100 *
b111100 )
b10000000100111101010110110000 +
1"
#611000
b110101001101111000100010001010 !
b110101001101111000100010001010 (
b110101001101111000100010001010 *
b111101 &
b10101000011111101110100101010 %
b10101000011111101110100101010 '
#615000
0"
#620000
b1111111011111101110111000111110 !
b1111111011111101110111000111110 (
b1111111011111101110111000111110 *
b110101001101111000100010001010 +
b111101 )
1"
#621000
b11110000010001101010101100011111 !
b11110000010001101010101100011111 (
b11110000010001101010101100011111 *
b111110 &
b10000101110101111001101000001011 %
b10000101110101111001101000001011 '
#625000
0"
#630000
b1100110011001001111000001001001 !
b1100110011001001111000001001001 (
b1100110011001001111000001001001 *
b111110 )
b11110000010001101010101100011111 +
1"
#631000
b10011001001001010001010010101111 !
b10011001001001010001010010101111 (
b10011001001001010001010010101111 *
b111111 &
b10111000100101111011111001110001 %
b10111000100101111011111001110001 '
#635000
0"
#640000
b11101010111000011110011111001111 !
b11101010111000011110011111001111 (
b11101010111000011110011111001111 *
b10011001001001010001010010101111 +
b111111 )
1"
#641000
b1110101001111000110101011100011 !
b1110101001111000110101011100011 (
b1110101001111000110101011100011 *
b1000000 &
b1000010111100100100000110000101 %
b1000010111100100100000110000101 '
#645000
0"
#650000
b101101011010110001011101001011 !
b101101011010110001011101001011 (
b101101011010110001011101001011 *
b1000000 )
b1110101001111000110101011100011 +
1"
#651000
b10010011010110010101100010101 !
b10010011010110010101100010101 (
b10010011010110010101100010101 *
b1000001 &
b100111111100100101010101001111 %
b100111111100100101010101001111 '
#655000
0"
#660000
b1001100110010001010101101111001 !
b1001100110010001010101101111001 (
b1001100110010001010101101111001 *
b10010011010110010101100010101 +
b1000001 )
1"
#661000
b11000010101000101011011001100101 !
b11000010101000101011011001100101 (
b11000010101000101011011001100101 *
b1000010 &
b10011101110011000110000000111011 %
b10011101110011000110000000111011 '
#665000
0"
#670000
b100011000100011100110100000101 !
b100011000100011100110100000101 (
b100011000100011100110100000101 *
b1000010 )
b11000010101000101011011001100101 +
1"
#671000
b10100010010010111010000000000100 !
b10100010010010111010000000000100 (
b10100010010010111010000000000100 *
b1000011 &
b11101000001100011001100111010 %
b11101000001100011001100111010 '
#675000
0"
#680000
b1100001100111010111001101000010 !
b1100001100111010111001101000010 (
b1100001100111010111001101000010 *
b10100010010010111010000000000100 +
b1000011 )
1"
#681000
b11101110100111001010000110 !
b11101110100111001010000110 (
b11101110100111001010000110 *
b1000100 &
b10111111001000110011001001111110 %
b10111111001000110011001001111110 '
#685000
0"
#690000
b11000110100110000001011110001010 !
b11000110100110000001011110001010 (
b11000110100110000001011110001010 *
b1000100 )
b11101110100111001010000110 +
1"
#691000
b10010000111110011000000100001 !
b10010000111110011000000100001 (
b10010000111110011000000100001 *
b1000101 &
b1010101010100100101100010101 %
b1010101010100100101100010101 '
#695000
0"
#700000
b101110111010001010101101010111 !
b101110111010001010101101010111 (
b101110111010001010101101010111 *
b10010000111110011000000100001 +
b1000101 )
1"
#701000
b10011101000101111111110000110011 !
b10011101000101111111110000110011 (
b10011101000101111111110000110011 *
b1000110 &
b1111000110110011001101111110001 %
b1111000110110011001101111110001 '
#705000
0"
#710000
b10110011000010011001010001010111 !
b10110011000010011001010001010111 (
b10110011000010011001010001010111 *
b1000110 )
b10011101000101111111110000110011 +
1"
#711000
b10100110110011000100010000111111 !
b10100110110011000100010000111111 (
b10100110110011000100010000111111 *
b1000111 &
b1101100100111000100101111011001 %
b1101100100111000100101111011001 '
#715000
0"
#720000
b10111010001101001101010001010111 !
b10111010001101001101010001010111 (
b10111010001101001101010001010111 *
b10100110110011000100010000111111 +
b1000111 )
1"
#721000
b1111110101110111000111111100000 !
b1111110101110111000111111100000 (
b1111110101110111000111111100000 *
b1001000 &
b110001001000110000011101100010 %
b110001001000110000011101100010 '
#725000
0"
#730000
b101110100110100010011100100010 !
b101110100110100010011100100010 (
b101110100110100010011100100010 *
b1001000 )
b1111110101110111000111111100000 +
1"
#731000
b100011101011010001101100001100 !
b100011101011010001101100001100 (
b100011101011010001101100001100 *
b1001001 &
b100110001101011111101101001100 %
b100110001101011111101101001100 '
#735000
0"
#740000
b1101101100100000011000101100100 !
b1101101100100000011000101100100 (
b1101101100100000011000101100100 *
b100011101011010001101100001100 +
b1001001 )
1"
#741000
b10010110111110111000101110110111 !
b10010110111110111000101110110111 (
b10010110111110111000101110110111 *
b1001010 &
b1001111101000010101010110011111 %
b1001111101000010101010110011111 '
#745000
0"
#750000
b1111101100110000110110100001101 !
b1111101100110000110110100001101 (
b1111101100110000110110100001101 *
b1001010 )
b10010110111110111000101110110111 +
1"
#751000
b1110101101100001011100011111101 !
b1110101101100001011100011111101 (
b1110101101100001011100011111101 *
b1001011 &
b1000111101110011010000110001111 %
b1000111101110011010000110001111 '
#755000
0"
#760000
b110011000110110001001110001001 !
b110011000110110001001110001001 (
b110011000110110001001110001001 *
b1110101101100001011100011111101 +
b1001011 )
1"
#761000
b1100111110011110001101111110010 !
b1100111110011110001101111110010 (
b1100111110011110001101111110010 *
b1001100 &
b1111100011011011010100111111000 %
b1111100011011011010100111111000 '
#765000
0"
#770000
b1001100000010111110000111011100 !
b1001100000010111110000111011100 (
b1001100000010111110000111011100 *
b1001100 )
b1100111110011110001101111110010 +
1"
#771000
b10101011011010111001100010011011 !
b10101011011010111001100010011011 (
b10101011011010111001100010011011 *
b1001101 &
b11011011110011010110000010110111 %
b11011011110011010110000010110111 '
#775000
0"
#780000
b110010101001001001000111101101 !
b110010101001001001000111101101 (
b110010101001001001000111101101 *
b10101011011010111001100010011011 +
b1001101 )
1"
#781000
b100110100110111000011111010101 !
b100110100110111000011111010101 (
b100110100110111000011111010101 *
b1001110 &
b11001111110001000101011010011111 %
b11001111110001000101011010011111 '
#785000
0"
#790000
b11100111110110110011001001001 !
b11100111110110110011001001001 (
b11100111110110110011001001001 *
b1001110 )
b100110100110111000011111010101 +
1"
#791000
b11111011101101001010010000000110 !
b11111011101101001010010000000110 (
b11111011101101001010010000000110 *
b1001111 &
b10101110011111011001010001011100 %
b10101110011111011001010001011100 '
#795000
0"
#800000
b10100101111001101101110001101000 !
b10100101111001101101110001101000 (
b10100101111001101101110001101000 *
b11111011101101001010010000000110 +
b1001111 )
1"
#801000
b10100101001101010000100001100111 !
b10100101001101010000100001100111 (
b10100101001101010000100001100111 *
b1010000 &
b10101101110010111100000001011011 %
b10101101110010111100000001011011 '
#805000
0"
#810000
b11111000001101011101000100101001 !
b11111000001101011101000100101001 (
b11111000001101011101000100101001 *
b1010000 )
b10100101001101010000100001100111 +
1"
#811000
b10001111010010000100100001010111 !
b10001111010010000100100001010111 (
b10001111010010000100100001010111 *
b1010001 &
b1000100110111100011011110001001 %
b1000100110111100011011110001001 '
#815000
0"
#820000
b1100011011011101100100000110111 !
b1100011011011101100100000110111 (
b1100011011011101100100000110111 *
b10001111010010000100100001010111 +
b1010001 )
1"
#821000
b11000011001111101100001011110111 !
b11000011001111101100001011110111 (
b11000011001111101100001011110111 *
b1010010 &
b10100100101011100011001001001001 %
b10100100101011100011001001001001 '
#825000
0"
#830000
b101011001010111011100000110111 !
b101011001010111011100000110111 (
b101011001010111011100000110111 *
b1010010 )
b11000011001111101100001011110111 +
1"
#831000
b1101110101000001100010010111110 !
b1101110101000001100010010111110 (
b1101110101000001100010010111110 *
b1010011 &
b11101000001000110011111011010000 %
b11101000001000110011111011010000 '
#835000
0"
#840000
b11000101011001001100100001001100 !
b11000101011001001100100001001100 (
b11000101011001001100100001001100 *
b1101110101000001100010010111110 +
b1010011 )
1"
#841000
b11001001010000000100101001010011 !
b11001001010000000100101001010011 (
b11001001010000000100101001010011 *
b1010100 &
b11101011111111101100000011010111 %
b11101011111111101100000011010111 '
#845000
0"
#850000
b1111110011111110101010101111101 !
b1111110011111110101010101111101 (
b1111110011111110101010101111101 *
b1010100 )
b11001001010000000100101001010011 +
1"
#851000
b111011010010001001000011110111 !
b111011010010001001000011110111 (
b111011010010001001000011110111 *
b1010101 &
b10101000110001111111110001010001 %
b10101000110001111111110001010001 '
#855000
0"
#860000
b11111010110010001111000111111 !
b11111010110010001111000111111 (
b11111010110010001111000111111 *
b111011010010001001000011110111 +
b1010101 )
1"
