circuit.v
`timescale 1ns / 1ps
`include "iob_lib.vh"

`define W = 32
module circuit
  #(
    parameter W = 32
    )
  (
   `INPUT(rst,1),
   `INPUT(clk,1),
   `INPUT(en,1),
   `OUTPUT(f,W)
   );
   `SIGNAL(cnt, 7)
   `SIGNAL(f_final, W)
   `SIGNAL(f_final_1, W)
   `SIGNAL(f_final_2, W)
   `SIGNAL2OUT(f, f_final)

   `REG_RE(clk, rst, 1'b0, en & (cnt!=99), f_final_1, f_final)
   `REG_RE(clk, rst, 1'b0, en & (cnt!=99), f_final_2, f_final_1)
   `COUNTER_RE(clk, rst, en & (cnt!=99), cnt)
   `COMB f_final = f_final_1 + f_final_2 + (cnt == 1'b1);
endmodule

circuit_tb.v
`timescale 1ns / 1ps
`include "iob_lib.vh"

`define W 128

module circuit_tb;

   `CLOCK(clk, 10)
   `RESET(rst, 1, 10)
   `SIGNAL(en, 1)
   `SIGNAL_OUT(f, `W)

   integer i;

   initial begin
      $dumpfile("circuit.vcd");
      $dumpvars();
      en=0;
      for (i=0; i<100; i=i+1) begin
         @(posedge clk) #1 en=1;
         $display("%d: %d",i+1, f);
      end

      @(posedge clk) #100 $finish;

   end

   circuit
     #(
       .W(`W)
       )
   c0
     (
      .rst(rst),
      .clk(clk),
      .en(en),
      .f(f)
      );


endmodule

circuit.vcd
$date
	Tue Nov 17 16:47:09 2020
$end
$version
	Icarus Verilog
$end
$timescale
	1ps
$end
$scope module circuit_tb $end
$var wire 128 ! f [127:0] $end
$var reg 1 " clk $end
$var reg 1 # en $end
$var reg 1 $ rst $end
$var integer 32 % i [31:0] $end
$scope module c0 $end
$var wire 1 " clk $end
$var wire 1 # en $end
$var wire 128 & f [127:0] $end
$var wire 1 $ rst $end
$var reg 7 ' cnt [6:0] $end
$var reg 128 ( f_final [127:0] $end
$var reg 128 ) f_final_1 [127:0] $end
$var reg 128 * f_final_2 [127:0] $end
$upscope $end
$upscope $end
$enddefinitions $end
#0
$dumpvars
bx *
bx )
bx (
bx '
bx &
b0 %
0$
0#
1"
bx !
$end
#1000
1$
#5000
0"
#10000
b0 !
b0 &
b0 (
b0 '
b0 *
b0 )
1"
#11000
b1 %
1#
0$
#15000
0"
#20000
b1 !
b1 &
b1 (
b1 '
1"
#21000
b10 %
#25000
0"
#30000
b10 '
b1 )
1"
#31000
b11 %
#35000
0"
#40000
b10 !
b10 &
b10 (
b1 *
b11 '
1"
#41000
b100 %
#45000
0"
#50000
b11 !
b11 &
b11 (
b100 '
b10 )
1"
#51000
b101 %
#55000
0"
#60000
b101 !
b101 &
b101 (
b11 )
b10 *
b101 '
1"
#61000
b110 %
#65000
0"
#70000
b1000 !
b1000 &
b1000 (
b110 '
b11 *
b101 )
1"
#71000
b111 %
#75000
0"
#80000
b1101 !
b1101 &
b1101 (
b1000 )
b101 *
b111 '
1"
#81000
b1000 %
#85000
0"
#90000
b10101 !
b10101 &
b10101 (
b1000 '
b1000 *
b1101 )
1"
#91000
b1001 %
#95000
0"
#100000
b100010 !
b100010 &
b100010 (
b10101 )
b1101 *
b1001 '
1"
#101000
b1010 %
#105000
0"
#110000
b110111 !
b110111 &
b110111 (
b1010 '
b10101 *
b100010 )
1"
#111000
b1011 %
#115000
0"
#120000
b1011001 !
b1011001 &
b1011001 (
b110111 )
b100010 *
b1011 '
1"
#121000
b1100 %
#125000
0"
#130000
b10010000 !
b10010000 &
b10010000 (
b1100 '
b110111 *
b1011001 )
1"
#131000
b1101 %
#135000
0"
#140000
b11101001 !
b11101001 &
b11101001 (
b10010000 )
b1011001 *
b1101 '
1"
#141000
b1110 %
#145000
0"
#150000
b101111001 !
b101111001 &
b101111001 (
b1110 '
b10010000 *
b11101001 )
1"
#151000
b1111 %
#155000
0"
#160000
b1001100010 !
b1001100010 &
b1001100010 (
b101111001 )
b11101001 *
b1111 '
1"
#161000
b10000 %
#165000
0"
#170000
b1111011011 !
b1111011011 &
b1111011011 (
b10000 '
b101111001 *
b1001100010 )
1"
#171000
b10001 %
#175000
0"
#180000
b11000111101 !
b11000111101 &
b11000111101 (
b1111011011 )
b1001100010 *
b10001 '
1"
#181000
b10010 %
#185000
0"
#190000
b101000011000 !
b101000011000 &
b101000011000 (
b10010 '
b1111011011 *
b11000111101 )
1"
#191000
b10011 %
#195000
0"
#200000
b1000001010101 !
b1000001010101 &
b1000001010101 (
b101000011000 )
b11000111101 *
b10011 '
1"
#201000
b10100 %
#205000
0"
#210000
b1101001101101 !
b1101001101101 &
b1101001101101 (
b10100 '
b101000011000 *
b1000001010101 )
1"
#211000
b10101 %
#215000
0"
#220000
b10101011000010 !
b10101011000010 &
b10101011000010 (
b1101001101101 )
b1000001010101 *
b10101 '
1"
#221000
b10110 %
#225000
0"
#230000
b100010100101111 !
b100010100101111 &
b100010100101111 (
b10110 '
b1101001101101 *
b10101011000010 )
1"
#231000
b10111 %
#235000
0"
#240000
b110111111110001 !
b110111111110001 &
b110111111110001 (
b100010100101111 )
b10101011000010 *
b10111 '
1"
#241000
b11000 %
#245000
0"
#250000
b1011010100100000 !
b1011010100100000 &
b1011010100100000 (
b11000 '
b100010100101111 *
b110111111110001 )
1"
#251000
b11001 %
#255000
0"
#260000
b10010010100010001 !
b10010010100010001 &
b10010010100010001 (
b1011010100100000 )
b110111111110001 *
b11001 '
1"
#261000
b11010 %
#265000
0"
#270000
b11101101000110001 !
b11101101000110001 &
b11101101000110001 (
b11010 '
b1011010100100000 *
b10010010100010001 )
1"
#271000
b11011 %
#275000
0"
#280000
b101111111101000010 !
b101111111101000010 &
b101111111101000010 (
b11101101000110001 )
b10010010100010001 *
b11011 '
1"
#281000
b11100 %
#285000
0"
#290000
b1001101100101110011 !
b1001101100101110011 &
b1001101100101110011 (
b11100 '
b11101101000110001 *
b101111111101000010 )
1"
#291000
b11101 %
#295000
0"
#300000
b1111101100010110101 !
b1111101100010110101 &
b1111101100010110101 (
b1001101100101110011 )
b101111111101000010 *
b11101 '
1"
#301000
b11110 %
#305000
0"
#310000
b11001011001000101000 !
b11001011001000101000 &
b11001011001000101000 (
b11110 '
b1001101100101110011 *
b1111101100010110101 )
1"
#311000
b11111 %
#315000
0"
#320000
b101001000101011011101 !
b101001000101011011101 &
b101001000101011011101 (
b11001011001000101000 )
b1111101100010110101 *
b11111 '
1"
#321000
b100000 %
#325000
0"
#330000
b1000010011110100000101 !
b1000010011110100000101 &
b1000010011110100000101 (
b100000 '
b11001011001000101000 *
b101001000101011011101 )
1"
#331000
b100001 %
#335000
0"
#340000
b1101011100011111100010 !
b1101011100011111100010 &
b1101011100011111100010 (
b1000010011110100000101 )
b101001000101011011101 *
b100001 '
1"
#341000
b100010 %
#345000
0"
#350000
b10101110000010011100111 !
b10101110000010011100111 &
b10101110000010011100111 (
b100010 '
b1000010011110100000101 *
b1101011100011111100010 )
1"
#351000
b100011 %
#355000
0"
#360000
b100011001100110011001001 !
b100011001100110011001001 &
b100011001100110011001001 (
b10101110000010011100111 )
b1101011100011111100010 *
b100011 '
1"
#361000
b100100 %
#365000
0"
#370000
b111000111101000110110000 !
b111000111101000110110000 &
b111000111101000110110000 (
b100100 '
b10101110000010011100111 *
b100011001100110011001001 )
1"
#371000
b100101 %
#375000
0"
#380000
b1011100001001111001111001 !
b1011100001001111001111001 &
b1011100001001111001111001 (
b111000111101000110110000 )
b100011001100110011001001 *
b100101 '
1"
#381000
b100110 %
#385000
0"
#390000
b10010101000111000000101001 !
b10010101000111000000101001 &
b10010101000111000000101001 (
b100110 '
b111000111101000110110000 *
b1011100001001111001111001 )
1"
#391000
b100111 %
#395000
0"
#400000
b11110001010000111010100010 !
b11110001010000111010100010 &
b11110001010000111010100010 (
b10010101000111000000101001 )
b1011100001001111001111001 *
b100111 '
1"
#401000
b101000 %
#405000
0"
#410000
b110000110010111111011001011 !
b110000110010111111011001011 &
b110000110010111111011001011 (
b101000 '
b10010101000111000000101001 *
b11110001010000111010100010 )
1"
#411000
b101001 %
#415000
0"
#420000
b1001110111101000110101101101 !
b1001110111101000110101101101 &
b1001110111101000110101101101 (
b110000110010111111011001011 )
b11110001010000111010100010 *
b101001 '
1"
#421000
b101010 %
#425000
0"
#430000
b1111111110000000110000111000 !
b1111111110000000110000111000 &
b1111111110000000110000111000 (
b101010 '
b110000110010111111011001011 *
b1001110111101000110101101101 )
1"
#431000
b101011 %
#435000
0"
#440000
b11001110101101001100110100101 !
b11001110101101001100110100101 &
b11001110101101001100110100101 (
b1111111110000000110000111000 )
b1001110111101000110101101101 *
b101011 '
1"
#441000
b101100 %
#445000
0"
#450000
b101001110011101010010111011101 !
b101001110011101010010111011101 &
b101001110011101010010111011101 (
b101100 '
b1111111110000000110000111000 *
b11001110101101001100110100101 )
1"
#451000
b101101 %
#455000
0"
#460000
b1000011101001010011111110000010 !
b1000011101001010011111110000010 &
b1000011101001010011111110000010 (
b101001110011101010010111011101 )
b11001110101101001100110100101 *
b101101 '
1"
#461000
b101110 %
#465000
0"
#470000
b1101101011100111110010101011111 !
b1101101011100111110010101011111 &
b1101101011100111110010101011111 (
b101110 '
b101001110011101010010111011101 *
b1000011101001010011111110000010 )
1"
#471000
b101111 %
#475000
0"
#480000
b10110001000110010010010011100001 !
b10110001000110010010010011100001 &
b10110001000110010010010011100001 (
b1101101011100111110010101011111 )
b1000011101001010011111110000010 *
b101111 '
1"
#481000
b110000 %
#485000
0"
#490000
b100011110100011010000101001000000 !
b100011110100011010000101001000000 &
b100011110100011010000101001000000 (
b110000 '
b1101101011100111110010101011111 *
b10110001000110010010010011100001 )
1"
#491000
b110001 %
#495000
0"
#500000
b111001111101001100010111100100001 !
b111001111101001100010111100100001 &
b111001111101001100010111100100001 (
b100011110100011010000101001000000 )
b10110001000110010010010011100001 *
b110001 '
1"
#501000
b110010 %
#505000
0"
#510000
b1011101110001100110011100101100001 !
b1011101110001100110011100101100001 &
b1011101110001100110011100101100001 (
b110010 '
b100011110100011010000101001000000 *
b111001111101001100010111100100001 )
1"
#511000
b110011 %
#515000
0"
#520000
b10010111101110110010110100010000010 !
b10010111101110110010110100010000010 &
b10010111101110110010110100010000010 (
b1011101110001100110011100101100001 )
b111001111101001100010111100100001 *
b110011 '
1"
#521000
b110100 %
#525000
0"
#530000
b11110101100000011001010000111100011 !
b11110101100000011001010000111100011 &
b11110101100000011001010000111100011 (
b110100 '
b1011101110001100110011100101100001 *
b10010111101110110010110100010000010 )
1"
#531000
b110101 %
#535000
0"
#540000
b110001101001111001100000101001100101 !
b110001101001111001100000101001100101 &
b110001101001111001100000101001100101 (
b11110101100000011001010000111100011 )
b10010111101110110010110100010000010 *
b110101 '
1"
#541000
b110110 %
#545000
0"
#550000
b1010000010101111100101010110001001000 !
b1010000010101111100101010110001001000 &
b1010000010101111100101010110001001000 (
b110110 '
b11110101100000011001010000111100011 *
b110001101001111001100000101001100101 )
1"
#551000
b110111 %
#555000
0"
#560000
b10000001111111110110001011011010101101 !
b10000001111111110110001011011010101101 &
b10000001111111110110001011011010101101 (
b1010000010101111100101010110001001000 )
b110001101001111001100000101001100101 *
b110111 '
1"
#561000
b111000 %
#565000
0"
#570000
b11010010010101110010110110001011110101 !
b11010010010101110010110110001011110101 &
b11010010010101110010110110001011110101 (
b111000 '
b1010000010101111100101010110001001000 *
b10000001111111110110001011011010101101 )
1"
#571000
b111001 %
#575000
0"
#580000
b101010100010101101001000001100110100010 !
b101010100010101101001000001100110100010 &
b101010100010101101001000001100110100010 (
b11010010010101110010110110001011110101 )
b10000001111111110110001011011010101101 *
b111001 '
1"
#581000
b111010 %
#585000
0"
#590000
b1000100110101011011011110111110010010111 !
b1000100110101011011011110111110010010111 &
b1000100110101011011011110111110010010111 (
b111010 '
b11010010010101110010110110001011110101 *
b101010100010101101001000001100110100010 )
1"
#591000
b111011 %
#595000
0"
#600000
b1101111011000001000100111001011000111001 !
b1101111011000001000100111001011000111001 &
b1101111011000001000100111001011000111001 (
b1000100110101011011011110111110010010111 )
b101010100010101101001000001100110100010 *
b111011 '
1"
#601000
b111100 %
#605000
0"
#610000
b10110100001101100100000110001001011010000 !
b10110100001101100100000110001001011010000 &
b10110100001101100100000110001001011010000 (
b111100 '
b1000100110101011011011110111110010010111 *
b1101111011000001000100111001011000111001 )
1"
#611000
b111101 %
#615000
0"
#620000
b100100011100101101100101101010100100001001 !
b100100011100101101100101101010100100001001 &
b100100011100101101100101101010100100001001 (
b10110100001101100100000110001001011010000 )
b1101111011000001000100111001011000111001 *
b111101 '
1"
#621000
b111110 %
#625000
0"
#630000
b111010111110011010000110011011101111011001 !
b111010111110011010000110011011101111011001 &
b111010111110011010000110011011101111011001 (
b111110 '
b10110100001101100100000110001001011010000 *
b100100011100101101100101101010100100001001 )
1"
#631000
b111111 %
#635000
0"
#640000
b1011111011011000111101100000110010011100010 !
b1011111011011000111101100000110010011100010 &
b1011111011011000111101100000110010011100010 (
b111010111110011010000110011011101111011001 )
b100100011100101101100101101010100100001001 *
b111111 '
1"
#641000
b1000000 %
#645000
0"
#650000
b10011010011001100001110010100010000010111011 !
b10011010011001100001110010100010000010111011 &
b10011010011001100001110010100010000010111011 (
b1000000 '
b111010111110011010000110011011101111011001 *
b1011111011011000111101100000110010011100010 )
1"
#651000
b1000001 %
#655000
0"
#660000
b11111001110100101001011110101000010110011101 !
b11111001110100101001011110101000010110011101 &
b11111001110100101001011110101000010110011101 (
b10011010011001100001110010100010000010111011 )
b1011111011011000111101100000110010011100010 *
b1000001 '
1"
#661000
b1000010 %
#665000
0"
#670000
b110010100001110001011010001001010011001011000 !
b110010100001110001011010001001010011001011000 &
b110010100001110001011010001001010011001011000 (
b1000010 '
b10011010011001100001110010100010000010111011 *
b11111001110100101001011110101000010110011101 )
1"
#671000
b1000011 %
#675000
0"
#680000
b1010001110000010110100101111110010101111110101 !
b1010001110000010110100101111110010101111110101 &
b1010001110000010110100101111110010101111110101 (
b110010100001110001011010001001010011001011000 )
b11111001110100101001011110101000010110011101 *
b1000011 '
1"
#681000
b1000100 %
#685000
0"
#690000
b10000100010010001000000000000111101001001001101 !
b10000100010010001000000000000111101001001001101 &
b10000100010010001000000000000111101001001001101 (
b1000100 '
b110010100001110001011010001001010011001011000 *
b1010001110000010110100101111110010101111110101 )
1"
#691000
b1000101 %
#695000
0"
#700000
b11010110000010011110100110000101111111001000010 !
b11010110000010011110100110000101111111001000010 &
b11010110000010011110100110000101111111001000010 (
b10000100010010001000000000000111101001001001101 )
b1010001110000010110100101111110010101111110101 *
b1000101 '
1"
#701000
b1000110 %
#705000
0"
#710000
b101011010010100100110100110001101101000010001111 !
b101011010010100100110100110001101101000010001111 &
b101011010010100100110100110001101101000010001111 (
b1000110 '
b10000100010010001000000000000111101001001001101 *
b11010110000010011110100110000101111111001000010 )
1"
#711000
b1000111 %
#715000
0"
#720000
b1000110000010111000101001100010011100111011010001 !
b1000110000010111000101001100010011100111011010001 &
b1000110000010111000101001100010011100111011010001 (
b101011010010100100110100110001101101000010001111 )
b11010110000010011110100110000101111111001000010 *
b1000111 '
1"
#721000
b1001000 %
#725000
0"
#730000
b1110001010101011101011110010100001001111101100000 !
b1110001010101011101011110010100001001111101100000 &
b1110001010101011101011110010100001001111101100000 (
b1001000 '
b101011010010100100110100110001101101000010001111 *
b1000110000010111000101001100010011100111011010001 )
1"
#731000
b1001001 %
#735000
0"
#740000
b10110111011000010110000111110110100110111000110001 !
b10110111011000010110000111110110100110111000110001 &
b10110111011000010110000111110110100110111000110001 (
b1110001010101011101011110010100001001111101100000 )
b1000110000010111000101001100010011100111011010001 *
b1001001 '
1"
#741000
b1001010 %
#745000
0"
#750000
b100101000101101110011100110001010110000110110010001 !
b100101000101101110011100110001010110000110110010001 &
b100101000101101110011100110001010110000110110010001 (
b1001010 '
b1110001010101011101011110010100001001111101100000 *
b10110111011000010110000111110110100110111000110001 )
1"
#751000
b1001011 %
#755000
0"
#760000
b111100000000110001001101110000001010111101111000010 !
b111100000000110001001101110000001010111101111000010 &
b111100000000110001001101110000001010111101111000010 (
b100101000101101110011100110001010110000110110010001 )
b10110111011000010110000111110110100110111000110001 *
b1001011 '
1"
#761000
b1001100 %
#765000
0"
#770000
b1100001000110011111101010100001100001000100101010011 !
b1100001000110011111101010100001100001000100101010011 &
b1100001000110011111101010100001100001000100101010011 (
b1001100 '
b100101000101101110011100110001010110000110110010001 *
b111100000000110001001101110000001010111101111000010 )
1"
#771000
b1001101 %
#775000
0"
#780000
b10011101000111010000111000010001101100000010100010101 !
b10011101000111010000111000010001101100000010100010101 &
b10011101000111010000111000010001101100000010100010101 (
b1100001000110011111101010100001100001000100101010011 )
b111100000000110001001101110000001010111101111000010 *
b1001101 '
1"
#781000
b1001110 %
#785000
0"
#790000
b11111110001101110000100010110011001101000111001101000 !
b11111110001101110000100010110011001101000111001101000 &
b11111110001101110000100010110011001101000111001101000 (
b1001110 '
b1100001000110011111101010100001100001000100101010011 *
b10011101000111010000111000010001101100000010100010101 )
1"
#791000
b1001111 %
#795000
0"
#800000
b110011011010101000001011011000100111001001001101111101 !
b110011011010101000001011011000100111001001001101111101 &
b110011011010101000001011011000100111001001001101111101 (
b11111110001101110000100010110011001101000111001101000 )
b10011101000111010000111000010001101100000010100010101 *
b1001111 '
1"
#801000
b1010000 %
#805000
0"
#810000
b1010011001100010110001111101111000000110010000111100101 !
b1010011001100010110001111101111000000110010000111100101 &
b1010011001100010110001111101111000000110010000111100101 (
b1010000 '
b11111110001101110000100010110011001101000111001101000 *
b110011011010101000001011011000100111001001001101111101 )
1"
#811000
b1010001 %
#815000
0"
#820000
b10000110100110111110011011000111100111111011010101100010 !
b10000110100110111110011011000111100111111011010101100010 &
b10000110100110111110011011000111100111111011010101100010 (
b1010011001100010110001111101111000000110010000111100101 )
b110011011010101000001011011000100111001001001101111101 *
b1010001 '
1"
#821000
b1010010 %
#825000
0"
#830000
b11011001110011010100101010110110101000101101011101000111 !
b11011001110011010100101010110110101000101101011101000111 &
b11011001110011010100101010110110101000101101011101000111 (
b1010010 '
b1010011001100010110001111101111000000110010000111100101 *
b10000110100110111110011011000111100111111011010101100010 )
1"
#831000
b1010011 %
#835000
0"
#840000
b101100000011010010011000101111110010000101000110010101001 !
b101100000011010010011000101111110010000101000110010101001 &
b101100000011010010011000101111110010000101000110010101001 (
b11011001110011010100101010110110101000101101011101000111 )
b10000110100110111110011011000111100111111011010101100010 *
b1010011 '
1"
#841000
b1010100 %
#845000
0"
#850000
b1000111010001101100111110000110100111001010110001111110000 !
b1000111010001101100111110000110100111001010110001111110000 &
b1000111010001101100111110000110100111001010110001111110000 (
b1010100 '
b11011001110011010100101010110110101000101101011101000111 *
b101100000011010010011000101111110010000101000110010101001 )
1"
#851000
b1010101 %
#855000
0"
#860000
b1110011010100111111010110110110011001001111111000010011001 !
b1110011010100111111010110110110011001001111111000010011001 &
b1110011010100111111010110110110011001001111111000010011001 (
b1000111010001101100111110000110100111001010110001111110000 )
b101100000011010010011000101111110010000101000110010101001 *
b1010101 '
1"
#861000
b1010110 %
#865000
0"
#870000
b10111010100110101100010100111101000000011010101010010001001 !
b10111010100110101100010100111101000000011010101010010001001 &
b10111010100110101100010100111101000000011010101010010001001 (
b1010110 '
b1000111010001101100111110000110100111001010110001111110000 *
b1110011010100111111010110110110011001001111111000010011001 )
1"
#871000
b1010111 %
#875000
0"
#880000
b100101101111011101011101011110011011001101010100010100100010 !
b100101101111011101011101011110011011001101010100010100100010 &
b100101101111011101011101011110011011001101010100010100100010 (
b10111010100110101100010100111101000000011010101010010001001 )
b1110011010100111111010110110110011001001111111000010011001 *
b1010111 '
1"
#881000
b1011000 %
#885000
0"
#890000
b111101000100010011000000000110000011010000101001100110101011 !
b111101000100010011000000000110000011010000101001100110101011 &
b111101000100010011000000000110000011010000101001100110101011 (
b1011000 '
b10111010100110101100010100111101000000011010101010010001001 *
b100101101111011101011101011110011011001101010100010100100010 )
1"
#891000
b1011001 %
#895000
0"
#900000
b1100010110011110000011101100100011110011101111101111011001101 !
b1100010110011110000011101100100011110011101111101111011001101 &
b1100010110011110000011101100100011110011101111101111011001101 (
b111101000100010011000000000110000011010000101001100110101011 )
b100101101111011101011101011110011011001101010100010100100010 *
b1011001 '
1"
#901000
b1011010 %
#905000
0"
#910000
b10011111111000000011011101101010100001101110100111100001111000 !
b10011111111000000011011101101010100001101110100111100001111000 &
b10011111111000000011011101101010100001101110100111100001111000 (
b1011010 '
b111101000100010011000000000110000011010000101001100110101011 *
b1100010110011110000011101100100011110011101111101111011001101 )
1"
#911000
b1011011 %
#915000
0"
#920000
b100000010101011110011111011001111000000001100100101011101000101 !
b100000010101011110011111011001111000000001100100101011101000101 &
b100000010101011110011111011001111000000001100100101011101000101 (
b10011111111000000011011101101010100001101110100111100001111000 )
b1100010110011110000011101100100011110011101111101111011001101 *
b1011011 '
1"
#921000
b1011100 %
#925000
0"
#930000
b110100010100011110111011000111001100001111011001100111110111101 !
b110100010100011110111011000111001100001111011001100111110111101 &
b110100010100011110111011000111001100001111011001100111110111101 (
b1011100 '
b10011111111000000011011101101010100001101110100111100001111000 *
b100000010101011110011111011001111000000001100100101011101000101 )
1"
#931000
b1011101 %
#935000
0"
#940000
b1010100101001111101011010100001000100010000111110010011100000010 !
b1010100101001111101011010100001000100010000111110010011100000010 &
b1010100101001111101011010100001000100010000111110010011100000010 (
b110100010100011110111011000111001100001111011001100111110111101 )
b100000010101011110011111011001111000000001100100101011101000101 *
b1011101 '
1"
#941000
b1011110 %
#945000
0"
#950000
b10001000111110011100010101101000010000100000010111111011010111111 !
b10001000111110011100010101101000010000100000010111111011010111111 &
b10001000111110011100010101101000010000100000010111111011010111111 (
b1011110 '
b110100010100011110111011000111001100001111011001100111110111101 *
b1010100101001111101011010100001000100010000111110010011100000010 )
1"
#951000
b1011111 %
#955000
0"
#960000
b11011101101000011001110000001001010100110001010110001110111000001 !
b11011101101000011001110000001001010100110001010110001110111000001 &
b11011101101000011001110000001001010100110001010110001110111000001 (
b10001000111110011100010101101000010000100000010111111011010111111 )
b1010100101001111101011010100001000100010000111110010011100000010 *
b1011111 '
1"
#961000
b1100000 %
#965000
0"
#970000
b101100110100110110110000101110001100101010001101110001010010000000 !
b101100110100110110110000101110001100101010001101110001010010000000 &
b101100110100110110110000101110001100101010001101110001010010000000 (
b1100000 '
b10001000111110011100010101101000010000100000010111111011010111111 *
b11011101101000011001110000001001010100110001010110001110111000001 )
1"
#971000
b1100001 %
#975000
0"
#980000
b1001000100001111001111110101111010111010000011000100011001001000001 !
b1001000100001111001111110101111010111010000011000100011001001000001 &
b1001000100001111001111110101111010111010000011000100011001001000001 (
b101100110100110110110000101110001100101010001101110001010010000000 )
b11011101101000011001110000001001010100110001010110001110111000001 *
b1100001 '
1"
#981000
b1100010 %
#985000
0"
#990000
b1110101010110110000101111011101100011111010100110010100011011000001 !
b1110101010110110000101111011101100011111010100110010100011011000001 &
b1110101010110110000101111011101100011111010100110010100011011000001 (
b1100010 '
b101100110100110110110000101110001100101010001101110001010010000000 *
b1001000100001111001111110101111010111010000011000100011001001000001 )
1"
#991000
b1100011 %
#995000
0"
#1000000
b10111101111000101010101110001100111011001010111110110111100100000010 !
b10111101111000101010101110001100111011001010111110110111100100000010 &
b10111101111000101010101110001100111011001010111110110111100100000010 (
b1110101010110110000101111011101100011111010100110010100011011000001 )
b1001000100001111001111110101111010111010000011000100011001001000001 *
b1100011 '
1"
#1001000
b1100100 %
